ChaseOaksTest1/__init__.py
ChaseOaksTest1/add.py
ChaseOaksTest1/power.py
ChaseOaksTest1/subtract.py
ChaseOaksTest1/extras/__init__.py
ChaseOaksTest1/extras/divide.py
ChaseOaksTest1/extras/multiply.py
ChaseOaksTest1-0.0.7.dist-info/METADATA
ChaseOaksTest1-0.0.7.dist-info/WHEEL
ChaseOaksTest1-0.0.7.dist-info/top_level.txt
ChaseOaksTest1-0.0.7.dist-info/RECORD
